somlib/__init__.py
somlib/__main__.py
somlib/func.py
somlib/py.typed
som_lib-0.0.6.dist-info/LICENSE
som_lib-0.0.6.dist-info/METADATA
som_lib-0.0.6.dist-info/WHEEL
som_lib-0.0.6.dist-info/top_level.txt
som_lib-0.0.6.dist-info/RECORD
