Metadata-Version: 2.1
Name: som-lib
Version: 0.0.6
Summary: SOM Lib (TODO: fix)
Home-page: https://github.com/xausssr/SOMLib
Author: Denis Kondaurov, Andrey Tolstyh, Maxim Elchugin
Author-email: xausssr@gmail.com
Maintainer: Andrey Tolstyh
Maintainer-email: xausssr@gmail.com
License: MIT License
Project-URL: Bug Tracker, https://github.com/xausssr/SOMLib/issues
Project-URL: Source Code, https://github.com/xausssr/SOMLib
Platform: any
Classifier: License :: OSI Approved :: MIT License
Classifier: Development Status :: 2 - Pre-Alpha
Classifier: Operating System :: OS Independent
Classifier: Intended Audience :: Science/Research
Classifier: Intended Audience :: Education
Classifier: Programming Language :: Python
Classifier: Programming Language :: Python :: 3
Classifier: Programming Language :: Python :: 3.6
Classifier: Programming Language :: Python :: 3.7
Classifier: Programming Language :: Python :: 3.8
Classifier: Programming Language :: Python :: 3.9
Classifier: Topic :: Software Development :: Libraries :: Python Modules
Classifier: Topic :: Scientific/Engineering
Requires-Python: <4,>3.7
